useasywin32com/__init__.py
useasywin32com/excel.py
useasywin32com/utils.py
useasywin32com/word.py
useasywin32com-0.0.1.dist-info/METADATA
useasywin32com-0.0.1.dist-info/WHEEL
useasywin32com-0.0.1.dist-info/top_level.txt
useasywin32com-0.0.1.dist-info/RECORD
